chkcrt/__init__.py
chkcrt/__main__.py
chkcrt-0.1.0.dist-info/entry_points.txt
chkcrt-0.1.0.dist-info/LICENSE
chkcrt-0.1.0.dist-info/WHEEL
chkcrt-0.1.0.dist-info/METADATA
chkcrt-0.1.0.dist-info/RECORD
