Metadata-Version: 2.1
Name: chkcrt
Version: 0.1.0
Summary: 
License: Apache-2.0
Author: Naglis Jonaitis
Author-email: hello@naglis.me
Requires-Python: >=3.8,<4.0
Classifier: License :: OSI Approved :: Apache Software License
Classifier: Programming Language :: Python :: 3
Classifier: Programming Language :: Python :: 3.8
Requires-Dist: cryptography (>=2.9.2,<3.0.0)
Requires-Dist: slackclient (>=2.6.1,<3.0.0)
